Flask_DSwagger/__init__.py
Flask_DSwagger-0.0.4.dist-info/DESCRIPTION.rst
Flask_DSwagger-0.0.4.dist-info/METADATA
Flask_DSwagger-0.0.4.dist-info/RECORD
Flask_DSwagger-0.0.4.dist-info/WHEEL
Flask_DSwagger-0.0.4.dist-info/metadata.json
Flask_DSwagger-0.0.4.dist-info/top_level.txt
