Metadata-Version: 2.0
Name: Flask-DSwagger
Version: 0.0.4
Summary: Convert Doc String OpenAPI 2.0 in a single endpoint
Home-page: https://github.com/abassel/Flask-DSwagger
Author: Alexandre Bassel
Author-email: abassel@gmail.com
License: MIT license
Keywords: OpenAPI 2.0,flask,swagger,docstring,doc-string
Platform: UNKNOWN
Classifier: Development Status :: 5 - Production/Stable
Classifier: Intended Audience :: Developers
Classifier: License :: OSI Approved :: MIT License
Classifier: Operating System :: Unix
Classifier: Operating System :: POSIX
Classifier: Operating System :: Microsoft :: Windows
Classifier: Programming Language :: Python
Classifier: Programming Language :: Python :: 2.7
Classifier: Programming Language :: Python :: 3
Classifier: Programming Language :: Python :: 3.3
Classifier: Programming Language :: Python :: 3.4
Classifier: Programming Language :: Python :: 3.5
Classifier: Programming Language :: Python :: 3.6
Requires-Dist: Flask (>=0.12.2)
Requires-Dist: PyYAML (>=3.12)
